flask_dynamo_session/__init__.py
flask_dynamo_session/__version__.py
flask_dynamo_session-0.0.3.dist-info/DESCRIPTION.rst
flask_dynamo_session-0.0.3.dist-info/METADATA
flask_dynamo_session-0.0.3.dist-info/RECORD
flask_dynamo_session-0.0.3.dist-info/WHEEL
flask_dynamo_session-0.0.3.dist-info/metadata.json
flask_dynamo_session-0.0.3.dist-info/top_level.txt
