Metadata-Version: 1.1
Name: flask-dynamo-session
Version: 0.0.3
Summary: Flask extension for storing session in dynamodb. Uses flask_dynamo.
Home-page: https://github.com/jaustinpage/flask-dynamo-session
Author: Austin Page
Author-email: jaustinpage@gmail.com
License: Apache License, Version 2.0
Keywords: flask dynamo dynamodb flask-dynamo
Platform: UNKNOWN
Classifier: License :: OSI Approved :: Apache Software License
Classifier: Development Status :: 2 - Pre-Alpha
Classifier: Programming Language :: Python :: 3.6
Classifier: Programming Language :: Python :: 2.7
